[
  {
  "nombre": "Matias",
  "apellido": "Vivone",
  "domicilio": "Medrano 500",
  "user": "matiasvivone@hotmail.com",
  "password": "1234",
  "fechaAlta": {},
  "legajo": 123123
},
  {
    "nombre": "Gustavo",
    "apellido": "Dipeppe",
    "domicilio": "Medrano 500",
    "user": "gustavodipeppe@hotmail.com",
    "password": "1234",
    "fechaAlta": {},
    "legajo": 123123
  },
  {
    "nombre": "Martin",
    "apellido": "Gauna",
    "domicilio": "Medrano 500",
    "user": "martingauna@hotmail.com",
    "password": "1234",
    "fechaAlta": {},
    "legajo": 123123
  }
  ,
  {
    "nombre": "Test",
    "apellido": "Admin",
    "domicilio": "Medrano 500",
    "user": "admin@admin",
    "password": "1234",
    "fechaAlta": {},
    "legajo": 123123
  }

]